Metadata-Version: 2.1
Name: plumbum
Version: 1.8.0
Summary: Plumbum: shell combinators library
Home-page: https://plumbum.readthedocs.io
Author: Tomer Filiba
Author-email: tomerfiliba@gmail.com
License: MIT
Project-URL: Bug Tracker, https://github.com/tomerfiliba/plumbum/issues
Project-URL: Changelog, https://plumbum.readthedocs.io/en/latest/changelog.html
Project-URL: Source, https://github.com/tomerfiliba/plumbum
Keywords: path,,local,,remote,,ssh,,shell,,pipe,,popen,,process,,execution,,color,,cli
Platform: POSIX
Platform: Windows
Classifier: Development Status :: 5 - Production/Stable
Classifier: License :: OSI Approved :: MIT License
Classifier: Operating System :: Microsoft :: Windows
Classifier: Operating System :: POSIX
Classifier: Programming Language :: Python :: 3
Classifier: Programming Language :: Python :: 3 :: Only
Classifier: Programming Language :: Python :: 3.6
Classifier: Programming Language :: Python :: 3.7
Classifier: Programming Language :: Python :: 3.8
Classifier: Programming Language :: Python :: 3.9
Classifier: Programming Language :: Python :: 3.10
Classifier: Programming Language :: Python :: 3.11
Classifier: Topic :: Software Development :: Build Tools
Classifier: Topic :: System :: Systems Administration
Provides: plumbum
Requires-Python: >=3.6
Provides-Extra: dev
Provides-Extra: docs
Provides-Extra: ssh
License-File: LICENSE
